setup.py
ebimporter.py.egg-info/PKG-INFO
ebimporter.py.egg-info/SOURCES.txt
ebimporter.py.egg-info/dependency_links.txt
ebimporter.py.egg-info/entry_points.txt
ebimporter.py.egg-info/requires.txt
ebimporter.py.egg-info/top_level.txt
importer/__init__.py
importer/card_utils.py
importer/cli.py
importer/core.py
importer/curses_helper.py
importer/errors.py
importer/utils.py